hemlock_io/__init__.py
hemlock_io-0.0.13.dist-info/METADATA
hemlock_io-0.0.13.dist-info/RECORD
hemlock_io-0.0.13.dist-info/WHEEL
hemlock_io-0.0.13.dist-info/top_level.txt
