Metadata-Version: 2.1
Name: hemlock-io
Version: 0.0.13
Summary: Helper package for transferring data to server
Home-page: https://github.com/hemlock-io/hemlock_io
Author: John Alexander Harris
Author-email: john@hemlock.io
License: UNKNOWN
Platform: UNKNOWN
Classifier: Programming Language :: Python :: 3
Classifier: License :: OSI Approved :: MIT License
Classifier: Operating System :: OS Independent
